{
  "date": "2026-07-16",
  "week": 5,
  "day": 4,
  "openingMessage": "In leadership, there are no words more important than trust.",
  "openingAttribution": "Mike Krzyzewski",
  "openingWhy": "When you write 0 ppm on a form, the next crew opens that line without re-testing — your signature is their gas test. Fudge one reading and every number you've ever signed becomes a question. There's no re-cal for a hand nobody trusts.",
  "formCounts": [
    {
      "name": "Raymundo Solis",
      "count": 44
    },
    {
      "name": "Nathan Contreras",
      "count": 35
    },
    {
      "name": "David Hammond",
      "count": 34
    },
    {
      "name": "Stefanie Kirschke",
      "count": 32
    },
    {
      "name": "Joseph Popillion",
      "count": 23
    },
    {
      "name": "Justin Fontenot",
      "count": 23
    },
    {
      "name": "Ralph Forbes",
      "count": 23
    },
    {
      "name": "Gage Gonzales",
      "count": 22
    },
    {
      "name": "Larry Jaramillo",
      "count": 22
    },
    {
      "name": "Caleb Smith",
      "count": 21
    },
    {
      "name": "Jordan Lemmons",
      "count": 21
    },
    {
      "name": "Marylou Guerra",
      "count": 21
    },
    {
      "name": "Baldemar Bracamontes",
      "count": 20
    },
    {
      "name": "David Jose Zamora",
      "count": 20
    },
    {
      "name": "Jacob Hernandez",
      "count": 20
    },
    {
      "name": "Andrew Bailey",
      "count": 19
    },
    {
      "name": "Cindy Smith",
      "count": 19
    },
    {
      "name": "Dermont Morgan",
      "count": 19
    },
    {
      "name": "Robert Wright",
      "count": 19
    },
    {
      "name": "Anthony Scott",
      "count": 18
    },
    {
      "name": "Rolando Flores",
      "count": 18
    },
    {
      "name": "Gary Briones",
      "count": 17
    },
    {
      "name": "Alfredo Vaquera",
      "count": 15
    },
    {
      "name": "Edward Carrillo",
      "count": 15
    },
    {
      "name": "Brianda Sandoval",
      "count": 14
    },
    {
      "name": "James Stephens",
      "count": 13
    },
    {
      "name": "Luis Zarate",
      "count": 13
    },
    {
      "name": "Dawson Drake",
      "count": 12
    },
    {
      "name": "Jimmy White",
      "count": 12
    },
    {
      "name": "Christian Lee",
      "count": 11
    },
    {
      "name": "Jaques Faulk",
      "count": 11
    },
    {
      "name": "Jaquez Faulk",
      "count": 11
    },
    {
      "name": "Marcos Morales",
      "count": 9
    },
    {
      "name": "Anthony Scott 1099",
      "count": 7
    },
    {
      "name": "Trevor Mckenzie",
      "count": 7
    },
    {
      "name": "Alexander Clubb",
      "count": 6
    },
    {
      "name": "Bobby Galindo",
      "count": 6
    },
    {
      "name": "Daniel Medrano",
      "count": 6
    },
    {
      "name": "Kyle Williams",
      "count": 6
    },
    {
      "name": "Allen White",
      "count": 4
    },
    {
      "name": "Barthol Bj Caesar",
      "count": 4
    },
    {
      "name": "Gael Antonio Avila",
      "count": 4
    },
    {
      "name": "John Blasingame",
      "count": 4
    },
    {
      "name": "Kelby Hammer Training",
      "count": 4
    },
    {
      "name": "Adam Holt",
      "count": 3
    },
    {
      "name": "Jeremy Norris",
      "count": 3
    },
    {
      "name": "Joshua Blassingame",
      "count": 3
    },
    {
      "name": "Justin Pack",
      "count": 2
    },
    {
      "name": "Jeremy Torrence",
      "count": 1
    },
    {
      "name": "Michael Jobe",
      "count": 1
    }
  ],
  "leadershipThought": "You are not just doing a job. You are building the next generation of people who will do this safely. That is what it means to be an Owl.",
  "opsDate": "2026-07-01",
  "opsContent": "<strong>Active Jobs (2026-07-01):</strong><br>No active jobs captured.<br><strong>Carry-Forward:</strong><br>None noted.",
  "lessonsLearned": null,
  "exxonMoments": "<strong>Good communication across the board with all teams on site to complete the</strong> <span style='font-size:12px;color:#888;font-style:italic;'>[Jeremy Norris]</span> <span style='font-size:12px;color:#666;'>(Atmospheric Monitoring)</span><br><span style='font-size:13px;'>Good communication across the board with all teams on site to complete the job scope</span><br><br><strong>Continuous gas monitoring was maintained, communication with the crew was e</strong> <span style='font-size:12px;color:#888;font-style:italic;'>[Stefanie Kirschke]</span> <span style='font-size:12px;color:#666;'>(Atmospheric Monitoring)</span><br><span style='font-size:13px;'>Continuous gas monitoring was maintained, communication with the crew was effective,</span><br><br><strong>Containment was broken the correct way with air on, AGT was done by us unde</strong> <span style='font-size:12px;color:#888;font-style:italic;'>[Alexander Clubb]</span> <span style='font-size:12px;color:#666;'>(Atmospheric Monitoring)</span><br><span style='font-size:13px;'>Containment was broken the correct way with air on, AGT was done by us under air.</span><br><br><strong>Observed stuffing box replacement with continuous atmospheric monitoring</strong> <span style='font-size:12px;color:#888;font-style:italic;'>[Stefanie Kirschke]</span> <span style='font-size:12px;color:#666;'>(Atmospheric Monitoring)</span><br><span style='font-size:13px;'>Observed stuffing box replacement with continuous atmospheric monitoring. The crew</span><br><br><strong>MT was extremely positive and understanding when we approached him with our</strong> <span style='font-size:12px;color:#888;font-style:italic;'>[Kelby Hammer Training]</span> <span style='font-size:12px;color:#666;'>(Atmospheric Monitoring)</span><br><span style='font-size:13px;'>MT was extremely positive and understanding when we approached him with our H2S</span>",
  "fieldNews": [
    {
      "type": "good",
      "headline": "Anthony Scott — everything went well and as expected",
      "detail": "Everything went well and as expected",
      "psms": "Operational Discipline"
    },
    {
      "type": "good",
      "headline": "Jeremy Norris — Good communication across the board with all teams on site to complete the",
      "detail": "Good communication across the board with all teams on site to complete the job scope",
      "psms": "Atmospheric Monitoring"
    },
    {
      "type": "good",
      "headline": "David Hammond — MT was well organized and knowledgeable",
      "detail": "MT was well organized and knowledgeable",
      "psms": "Operational Discipline"
    },
    {
      "type": "good",
      "headline": "Jordan Lemmons — We stopped the job to get a greasing crew out",
      "detail": "We stopped the job to get a greasing crew out",
      "psms": "Operational Discipline"
    },
    {
      "type": "good",
      "headline": "Caleb Smith — Everyone on location performed well on every task",
      "detail": "Everyone on location performed well on every task.",
      "psms": "Operational Discipline"
    },
    {
      "type": "flag",
      "headline": "SM Energy #112 — 6,000 ppm H2S / 2% CO2 (carry-forward from 7/10)",
      "detail": "Michael Hutt reported it Friday. Confirm current readings before any entry or first break this week.",
      "psms": "Confined Space · Wk 5"
    },
    {
      "type": "flag",
      "headline": "Two driving near-misses flagged Friday — stay heads-up on the road",
      "detail": "Jordan Lemmons (swerving driver, Jal 128) and Alex Clubb (service truck into his lane at 75 mph). The drive is part of the job.",
      "psms": "Driving · Wk 6"
    }
  ],
  "todaysChallenge": "If the numbers say stop today, stop — even if the whole location is waiting on you. That call takes courage once. It builds a reputation forever.",
  "todaysChallengeSubtext": "“Courage and confidence are what decision making is all about.” — Mike Krzyzewski",
  "compliance": {
    "weekOf": "Week of July 13, 2026",
    "metrics": [
      {
        "label": "Daily H2S Forms (D/N)",
        "done": 152,
        "total": 172
      },
      {
        "label": "Trailer Inspections",
        "done": 33,
        "total": 41
      },
      {
        "label": "Trailer Readiness Forms",
        "done": 20,
        "total": 28
      }
    ],
    "footerNote": "Live from Daily Internal Compliance — Mon through Wed 07/15"
  }
}